{
  "places": [
    {
      "id": 1,
      "name": "By Hand Pizza Café",
      "city": "Chiang Mai",
      "country": "Thailand",
      "lat": 18.7923,
      "lng": 98.9967,
      "review": "Wood-fired artisan pizza with naturally fermented dough. Suu says it's like kimchi - the fermentation makes everything better! The Summer Pizza with fresh ricotta is absolutely divine. 🥢➡️🍕",
      "rating": 5,
      "image": "https://picsum.photos/seed/byhandpizza/400/300",
      "address": "25 Moon Muang Road Soi 7, Si Phum, Chiang Mai",
      "phone": "+66 638828195",
      "website": "https://byhandpizza.com",
      "hours": "11:00 - 22:30 (365 days a year)",
      "specialty": "Wood-fired Neapolitan-style pizza",
      "priceRange": "180-340 THB",
      "suuQuote": "The fermented dough reminds me of home - just like kimchi, time makes everything more delicious!",
      "visitDate": "2023-11-15",
      "mustTry": ["Summer Pizza", "Margherita", "Honey Lime Soda"]
    },
    {
      "id": 2,
      "name": "Freely Pizza",
      "city": "Chiang Mai", 
      "country": "Thailand",
      "lat": 18.7965,
      "lng": 98.9912,
      "review": "Hidden gem with incredible thin-crust pizza and a cozy atmosphere. The owners are so passionate about their craft, reminds me of Korean dedication to perfection!",
      "rating": 4,
      "image": "https://picsum.photos/seed/freelypizza/400/300",
      "address": "Old City, Chiang Mai",
      "specialty": "Thin-crust artisan pizza",
      "priceRange": "150-280 THB",
      "suuQuote": "Small place, big flavors - just how I like my pizza adventures!",
      "visitDate": "2023-11-16",
      "mustTry": ["Quattro Stagioni", "Prosciutto", "Truffle Pizza"]
    },
    {
      "id": 3,
      "name": "Chiang Mai Slice",
      "city": "Chiang Mai",
      "country": "Thailand",
      "lat": 18.7883,
      "lng": 98.9853,
      "review": "Cozy spot with thin crust perfection and the friendliest staff. Their spicy tom yum pizza is a fusion masterpiece!",
      "rating": 4,
      "image": "https://picsum.photos/seed/pizza1/400/300",
      "address": "Nimman Road, Chiang Mai",
      "specialty": "Thai-Italian fusion pizza",
      "priceRange": "120-250 THB",
      "suuQuote": "They put tom yum on pizza and it WORKS! Fusion done right.",
      "visitDate": "2023-10-20",
      "mustTry": ["Tom Yum Pizza", "Green Curry Pizza", "Classic Margherita"]
    },
    {
      "id": 4,
      "name": "Seoul Pizza Lab",
      "city": "Seoul",
      "country": "South Korea",
      "lat": 37.5665,
      "lng": 126.9780,
      "review": "Creative toppings and great atmosphere. Being back home in Seoul, this place serves Korean-style corn and sweet potato pizza that actually works!",
      "rating": 5,
      "image": "https://picsum.photos/seed/pizza2/400/300",
      "address": "Gangnam District, Seoul",
      "specialty": "Korean-style creative pizza",
      "priceRange": "15,000-28,000 KRW",
      "suuQuote": "Finally, pizza that understands Korean taste buds! The corn pizza here is legendary.",
      "visitDate": "2023-12-01",
      "mustTry": ["Sweet Potato Pizza", "Corn & Mayo", "Bulgogi Pizza"]
    },
    {
      "id": 5,
      "name": "Napoli Classic",
      "city": "Napoli",
      "country": "Italy",
      "lat": 40.8518,
      "lng": 14.2681,
      "review": "Authentic Neapolitan pies straight from the oven. This is where pizza was born, and you can taste centuries of tradition in every bite!",
      "rating": 5,
      "image": "https://picsum.photos/seed/pizza3/400/300",
      "address": "Via dei Tribunali, Naples",
      "specialty": "Traditional Neapolitan pizza",
      "priceRange": "8-15 EUR",
      "suuQuote": "The birthplace of pizza - like visiting the kimchi capital of Korea!",
      "visitDate": "2023-09-10",
      "mustTry": ["Pizza Margherita", "Marinara", "Quattro Stagioni"]
    },
    {
      "id": 6,
      "name": "Tokyo Tomato",
      "city": "Tokyo",
      "country": "Japan",
      "lat": 35.6895,
      "lng": 139.6917,
      "review": "Fusion-style slices with a local twist. Japanese attention to detail meets Italian passion - the teriyaki chicken pizza is surprisingly amazing!",
      "rating": 4,
      "image": "https://picsum.photos/seed/pizza4/400/300",
      "address": "Shibuya District, Tokyo",
      "specialty": "Japanese-Italian fusion",
      "priceRange": "1,200-2,800 JPY",
      "suuQuote": "Only the Japanese could make teriyaki pizza work this well!",
      "visitDate": "2023-08-22",
      "mustTry": ["Teriyaki Chicken", "Seafood Special", "Mayo Corn"]
    },
    {
      "id": 7,
      "name": "Berlin Dough",
      "city": "Berlin",
      "country": "Germany",
      "lat": 52.52,
      "lng": 13.405,
      "review": "Late-night favorite with crispy bases and generous toppings. Perfect after exploring Berlin's amazing food scene!",
      "rating": 3,
      "image": "https://picsum.photos/seed/pizza5/400/300",
      "address": "Kreuzberg, Berlin",
      "specialty": "Late-night pizza",
      "priceRange": "8-16 EUR",
      "suuQuote": "Great for late-night munchies, though nothing beats Korean fried chicken at 3am!",
      "visitDate": "2023-07-05",
      "mustTry": ["Döner Pizza", "Currywurst Pizza", "Classic Salami"]
    },
    {
      "id": 8,
      "name": "NYC Pie Co.",
      "city": "New York",
      "country": "USA",
      "lat": 40.7128,
      "lng": -74.006,
      "review": "Classic New York slices done right. Huge, foldable slices that remind me why NYC pizza is legendary!",
      "rating": 4,
      "image": "https://picsum.photos/seed/pizza6/400/300",
      "address": "Brooklyn, New York",
      "specialty": "New York-style pizza",
      "priceRange": "$3-8 USD",
      "suuQuote": "You haven't lived until you've folded a NYC slice like a pro!",
      "visitDate": "2023-06-18",
      "mustTry": ["Classic Cheese", "Pepperoni", "White Pizza"]
    },
    {
      "id": 9,
      "name": "Melbourne Mozzarella",
      "city": "Melbourne",
      "country": "Australia",
      "lat": -37.8136,
      "lng": 144.9631,
      "review": "Laid-back spot with rich flavors and amazing coffee. The Aussie hospitality makes every bite better!",
      "rating": 4,
      "image": "https://picsum.photos/seed/pizza7/400/300",
      "address": "Fitzroy, Melbourne",
      "specialty": "Artisan wood-fired pizza",
      "priceRange": "$18-32 AUD",
      "suuQuote": "Great pizza and even better coffee - the Australian way!",
      "visitDate": "2023-05-12",
      "mustTry": ["Prosciutto & Rocket", "Lamb & Rosemary", "Vegetarian Supreme"]
    },
    {
      "id": 10,
      "name": "Rio Pizza House",
      "city": "Rio de Janeiro",
      "country": "Brazil",
      "lat": -22.9068,
      "lng": -43.1729,
      "review": "Beachside pizza with tropical vibes. Eating pizza while watching the sunset over Copacabana - pure magic!",
      "rating": 3,
      "image": "https://picsum.photos/seed/pizza8/400/300",
      "address": "Copacabana, Rio de Janeiro",
      "specialty": "Brazilian-style pizza",
      "priceRange": "25-45 BRL",
      "suuQuote": "Pizza by the beach hits different - like Korean chicken and beer by the Han River!",
      "visitDate": "2023-04-08",
      "mustTry": ["Calabresa", "Portuguesa", "Tropical Fruits"]
    },
    {
      "id": 11,
      "name": "Parisian Pie",
      "city": "Paris",
      "country": "France",
      "lat": 48.8566,
      "lng": 2.3522,
      "review": "Charming bistro serving gourmet slices with French flair. They put truffle on everything and somehow it works!",
      "rating": 5,
      "image": "https://picsum.photos/seed/pizza9/400/300",
      "address": "Le Marais, Paris",
      "specialty": "French gourmet pizza",
      "priceRange": "16-28 EUR",
      "suuQuote": "Leave it to the French to make pizza fancy - and delicious!",
      "visitDate": "2023-03-25",
      "mustTry": ["Truffle & Mushroom", "Duck Confit", "Goat Cheese & Honey"]
    },
    {
      "id": 12,
      "name": "Toronto Toppings",
      "city": "Toronto",
      "country": "Canada",
      "lat": 43.6532,
      "lng": -79.3832,
      "review": "Modern take on traditional pizza with Canadian hospitality. The maple bacon pizza is surprisingly not too sweet!",
      "rating": 4,
      "image": "https://picsum.photos/seed/pizza10/400/300",
      "address": "Kensington Market, Toronto",
      "specialty": "Canadian-style gourmet pizza",
      "priceRange": "$14-26 CAD",
      "suuQuote": "They put maple syrup on pizza and apologized for how good it was - so Canadian!",
      "visitDate": "2023-02-14",
      "mustTry": ["Maple Bacon", "Poutine Pizza", "Montreal Smoked Meat"]
    }
  ]
} 